cs_crypt/__init__.py
cs_crypt/tests/__init__.py
cs_crypt/tests/test.py
cs_crypt-0.0.2.dist-info/METADATA
cs_crypt-0.0.2.dist-info/WHEEL
cs_crypt-0.0.2.dist-info/top_level.txt
cs_crypt-0.0.2.dist-info/RECORD
