Metadata-Version: 2.1
Name: cs-crypt
Version: 0.0.2
Summary: Encryption helper for compute-studio.
Home-page: https://github.com/compute-tooling/compute-studio/crypt
Author: Hank Doupe
Author-email: hank@compute.studio
License: UNKNOWN
Platform: UNKNOWN
Classifier: Programming Language :: Python :: 3
Classifier: License :: OSI Approved :: GNU Affero General Public License v3
Classifier: Operating System :: OS Independent
Requires-Dist: cryptography
